CHANGELOG.md
CONTRIBUTORS.md
LICENSE.txt
MANIFEST.in
README.md
setup.cfg
setup.py
examples/example.py
tests/conftest.py
tests/test_import.py
tests/test_raw_query.py
tests/zdesk_common.py
tests/zdtestcfg.py.example
tests/__pycache__/conftest.cpython-310-pytest-7.1.2.pyc
tests/__pycache__/conftest.cpython-39-pytest-7.1.2.pyc
tests/__pycache__/test_import.cpython-310-pytest-7.1.2.pyc
tests/__pycache__/test_import.cpython-39-pytest-7.1.2.pyc
tests/__pycache__/test_raw_query.cpython-310-pytest-7.1.2.pyc
tests/__pycache__/test_raw_query.cpython-39-pytest-7.1.2.pyc
tests/__pycache__/zdesk_common.cpython-310.pyc
tests/__pycache__/zdesk_common.cpython-39.pyc
tests/tickets/test_tickets.py
tests/tickets/__pycache__/test_tickets.cpython-310-pytest-7.1.2.pyc
tests/tickets/__pycache__/test_tickets.cpython-39-pytest-7.1.2.pyc
zdesk/__init__.py
zdesk/zdesk.py
zdesk/zdesk_api.py
zdesk.egg-info/PKG-INFO
zdesk.egg-info/SOURCES.txt
zdesk.egg-info/dependency_links.txt
zdesk.egg-info/requires.txt
zdesk.egg-info/top_level.txt