Metadata-Version: 1.1
Name: zdesk
Version: 2.8.0
Summary: Zendesk API generated directly from developer.zendesk.com
Home-page: https://github.com/fprimex/zdesk
Author: Brent Woodruff
Author-email: brent@fprimex.com
License: LICENSE.txt
Keywords: zendesk api helpdesk
Platform: UNKNOWN
Classifier: Development Status :: 5 - Production/Stable
Classifier: Intended Audience :: Developers
Classifier: License :: OSI Approved :: MIT License
Classifier: Topic :: Software Development :: Libraries :: Python Modules
Classifier: Topic :: Internet
Classifier: Programming Language :: Python :: 2
Classifier: Programming Language :: Python :: 3
